<?xml version="1.0" encoding="UTF-8"?>
<itaEngine>
     <engineModel el_nome="cwbBtaAnprSubentratiUtils" el_tipo="1" el_colonne="0" tipo_nome="generico" tipo_tag="form">
          <properties>
               <action><![CDATA[#cwbBtaAnprSubentratiUtils]]></action>
               <class><![CDATA[ita-app ita-dialog ita-layout-diag {title:"Allineamento tabella Comuni Subentrati",width:900,height:500,modal:true,position:'center',modelBackend:'cwbBtaAnprSubentratiUtils'}]]></class>
          </properties>
          <engineElement el_nome="workspace" el_tipo="7" el_colonne="0" disp_colspan="0" disp_rowspan="0" disp_acapo="0" tipo_nome="generico" tipo_tag="div">
               <properties>
                    <class><![CDATA[ita-layout-center ita-workspace]]></class>
               </properties>
               <engineElement el_nome="div_label" el_tipo="70" el_colonne="0" disp_colspan="0" disp_rowspan="0" disp_acapo="0" tipo_nome="ita-box" tipo_tag="div">
                    <properties>
                         <style><![CDATA[width:75%;height:25%;margin-left: 100px]]></style>
                    </properties>
                    <tipoProperties>
                         <class><![CDATA[ita-box ui-widget-content ui-corner-all]]></class>
                    </tipoProperties>
                    <engineElement el_nome="spazio" el_tipo="72" el_colonne="0" disp_colspan="0" disp_rowspan="0" disp_acapo="0" tipo_nome="generico" tipo_tag="br">
                    </engineElement>
                    <engineElement el_nome="label_message" el_tipo="92" el_colonne="0" disp_colspan="0" disp_rowspan="0" disp_acapo="0" tipo_nome="ita-span" tipo_tag="span">
                         <properties>
                              <value><![CDATA[L'operazione di allineamento Comuni Subentrati esegue l'importazione del file in formato .xlsx. Il file da importare dovrà essere scaricato dal sito https://www.anpr.interno.it/portale/tabelle-di-riferimento, voce "Comuni Subentrati".]]></value>
                              <style><![CDATA[font-style: italic;font-size:18px]]></style>
                         </properties>
                         <tipoProperties>
                              <class><![CDATA[ita-span]]></class>
                         </tipoProperties>
                    </engineElement>
               </engineElement>
          </engineElement>
          <engineElement el_nome="buttonBar" el_tipo="7" el_colonne="0" disp_colspan="0" disp_rowspan="0" disp_acapo="0" tipo_nome="generico" tipo_tag="div">
               <properties>
                    <style><![CDATA[width:180px;]]></style>
                    <class><![CDATA[ita-layout-east ita-buttonbar ita-buttonbar-medium]]></class>
               </properties>
               <engineElement el_nome="Import" el_tipo="62" el_colonne="0" disp_colspan="0" disp_rowspan="0" disp_acapo="0" tipo_nome="ita-button" tipo_tag="button">
                    <properties>
                         <value><![CDATA[Import]]></value>
                         <class><![CDATA[{iconLeft:'ui-icon ui-icon-arrowthick-1-w'}]]></class>
                         <style><![CDATA[width: 98%; margin-bottom: 15px; padding: 4px 2px;]]></style>
                    </properties>
                    <tipoProperties>
                         <class><![CDATA[ita-button ita-element-animate]]></class>
                    </tipoProperties>
               </engineElement>
          </engineElement>
          <engineElement el_nome="divAppoggio" el_tipo="7" el_colonne="0" disp_colspan="0" disp_rowspan="0" disp_acapo="0" tipo_nome="generico" tipo_tag="div">
               <properties>
                    <class><![CDATA[ita-hidden]]></class>
               </properties>
          </engineElement>
     </engineModel>
     <info>
          <date><![CDATA[28/11/2019]]></date>
          <time><![CDATA[13:21:05]]></time>
          <user><![CDATA[PALC1]]></user>
          <modelSHA><![CDATA[c90064d54c93aef2eceb8f24792cb086c535f2cb]]></modelSHA>
     </info></itaEngine>