<?xml version="1.0" encoding="UTF-8"?>
<itaEngine>
     <engineModel el_nome="proAccMail" el_tipo="1" el_colonne="0" tipo_nome="generico" tipo_tag="form">
          <properties>
               <action><![CDATA[#proAccMail]]></action>
               <class><![CDATA[ita-dialog ita-layout-diag {maximized:false,title:"Gestione account mail protocollo",width:700,height:220,modal:true}]]></class>
          </properties>
          <engineElement el_nome="workSpace" el_tipo="74" el_colonne="0" disp_colspan="0" disp_rowspan="0" disp_acapo="0" tipo_nome="ita-div" tipo_tag="div">
               <properties>
                    <style><![CDATA[width:950;]]></style>
                    <class><![CDATA[ita-layout-center ita-workspace]]></class>
               </properties>
               <tipoProperties>
                    <class><![CDATA[ita-div]]></class>
               </tipoProperties>
               <engineElement el_nome="divGestione" el_tipo="90" el_colonne="0" disp_colspan="0" disp_rowspan="0" disp_acapo="0" tipo_nome="ita-data-page" tipo_tag="div">
                    <properties>
                         <class><![CDATA[ita-edit-page]]></class>
                    </properties>
                    <tipoProperties>
                         <class><![CDATA[ita-data-page]]></class>
                    </tipoProperties>
                    <engineElement el_nome="ACCOUNT[EMAIL]" el_tipo="85" el_colonne="0" disp_colspan="0" disp_rowspan="0" disp_acapo="1" tipo_nome="ita-readonly" tipo_tag="text">
                         <label class="sx input" style="width:120px"><![CDATA[Indirizzo Email]]></label>
                         <properties>
                              <size><![CDATA[40]]></size>
                         </properties>
                         <tipoProperties>
                              <readonly><![CDATA[readonly]]></readonly>
                              <class><![CDATA[ita-readonly ita-edit]]></class>
                         </tipoProperties>
                    </engineElement>
                    <engineElement el_nome="divSpazio" el_tipo="7" el_colonne="0" disp_colspan="0" disp_rowspan="0" disp_acapo="0" tipo_nome="generico" tipo_tag="div">
                         <properties>
                              <style><![CDATA[height:2px; width: 420px; margin:3px;]]></style>
                         </properties>
                    </engineElement>
                    <engineElement el_nome="ACCOUNT[SCAR_AUTO]" el_tipo="89" el_colonne="0" disp_colspan="0" disp_rowspan="0" disp_acapo="1" tipo_nome="ita-checkbox" tipo_tag="checkbox">
                         <label class="sx ui-widget input" style="width:300px"><![CDATA[Scarico automatico mail]]></label>
                         <tipoProperties>
                              <class><![CDATA[ita-edit ita-checkbox]]></class>
                         </tipoProperties>
                    </engineElement>
                    <engineElement el_nome="ACCOUNT[PROT_AUTO]" el_tipo="89" el_colonne="0" disp_colspan="0" disp_rowspan="0" disp_acapo="1" tipo_nome="ita-checkbox" tipo_tag="checkbox">
                         <label class="sx ui-widget input" style="width:300px"><![CDATA[Protocollazione automatica arrivi interoperabili]]></label>
                         <tipoProperties>
                              <class><![CDATA[ita-edit ita-checkbox]]></class>
                         </tipoProperties>
                    </engineElement>
               </engineElement>
          </engineElement>
          <engineElement el_nome="buttonBar" el_tipo="7" el_colonne="0" disp_colspan="0" disp_rowspan="0" disp_acapo="0" tipo_nome="generico" tipo_tag="div">
               <properties>
                    <style><![CDATA[width:150px;]]></style>
                    <class><![CDATA[ita-layout-east ita-buttonbar]]></class>
               </properties>
               <engineElement el_nome="Conferma" el_tipo="66" el_colonne="0" disp_colspan="0" disp_rowspan="0" disp_acapo="1" tipo_nome="ita-button-validate" tipo_tag="button">
                    <properties>
                         <value><![CDATA[F4-Conferma]]></value>
                         <class><![CDATA[ita-button-commit {iconLeft:'ui-icon ui-icon-disk',shortCut:'f4'}]]></class>
                         <style><![CDATA[width:99%; height:22px;]]></style>
                    </properties>
                    <tipoProperties>
                         <class><![CDATA[ita-button-validate ita-element-animate]]></class>
                    </tipoProperties>
               </engineElement>
          </engineElement>
          <engineElement el_nome="divAppoggio" el_tipo="7" el_colonne="0" disp_colspan="0" disp_rowspan="0" disp_acapo="0" tipo_nome="generico" tipo_tag="div">
               <properties>
                    <class><![CDATA[ita-hidden]]></class>
               </properties>
               <engineElement el_nome="ACCOUNT[ID]" el_tipo="54" el_colonne="0" disp_colspan="0" disp_rowspan="0" disp_acapo="0" tipo_nome="invisible" tipo_tag="text">
                    <tipoProperties>
                         <style><![CDATA[visibility: hidden;]]></style>
                    </tipoProperties>
               </engineElement>
          </engineElement>
     </engineModel>
     <info>
          <date><![CDATA[07/11/2017]]></date>
          <time><![CDATA[15:30:40]]></time>
          <user><![CDATA[a.mucci]]></user>
          <modelSHA><![CDATA[c042f8ec52a98003a611f25c60b4592cb1a5a102]]></modelSHA>
     </info></itaEngine>