<?xml version="1.0" encoding="UTF-8"?>
<itaEngine>
     <engineModel el_nome="proElencoProtocolliPortlet" el_tipo="1" el_colonne="1" tipo_nome="generico" tipo_tag="form">
          <properties>
               <action><![CDATA[#proElencoProtocolliPortlet]]></action>
               <class><![CDATA[ita-app-portlet ita-layout-diag]]></class>
          </properties>
          <engineElement el_nome="divElenco" el_tipo="7" el_colonne="0" disp_colspan="0" disp_rowspan="0" disp_acapo="0" tipo_nome="generico" tipo_tag="div">
               <properties>
                    <style><![CDATA[height:550px;]]></style>
                    <class><![CDATA[ita-layout-center]]></class>
               </properties>
               <engineElement el_nome="divInfo" el_tipo="70" el_colonne="0" disp_colspan="0" disp_rowspan="0" disp_acapo="0" tipo_nome="ita-box" tipo_tag="div">
                    <properties>
                         <class><![CDATA[ita-data-page]]></class>
                    </properties>
                    <tipoProperties>
                         <class><![CDATA[ita-box ui-widget-content ui-corner-all]]></class>
                    </tipoProperties>
                    <engineElement el_nome="selectUffici" el_tipo="80" el_colonne="0" disp_colspan="0" disp_rowspan="0" disp_acapo="0" tipo_nome="ita-select" tipo_tag="select">
                         <label class="top input"><![CDATA[Selezione]]></label>
                         <properties>
                              <class><![CDATA[ita-edit-onchange]]></class>
                         </properties>
                         <tipoProperties>
                              <class><![CDATA[ita-select ita-edit]]></class>
                         </tipoProperties>
                    </engineElement>
                    <engineElement el_nome="divMessaggio" el_tipo="70" el_colonne="0" disp_colspan="0" disp_rowspan="0" disp_acapo="0" tipo_nome="ita-box" tipo_tag="div">
                         <properties>
                              <style><![CDATA[display:inline-block;height:26px;vertical-align:bottom;font-size:16px;padding-left: 4px;padding-right: 4px;padding-top: 6px;]]></style>
                         </properties>
                         <tipoProperties>
                              <class><![CDATA[ita-box ui-widget-content ui-corner-all]]></class>
                         </tipoProperties>
                    </engineElement>
                    <engineElement el_nome="btnCerca" el_tipo="62" el_colonne="0" disp_colspan="0" disp_rowspan="0" disp_acapo="0" tipo_nome="ita-button" tipo_tag="button">
                         <properties>
                              <value><![CDATA[Cerca]]></value>
                              <class><![CDATA[{iconLeft:'ui-icon ui-icon-search'}]]></class>
                              <style><![CDATA[width:80px;height:34px;vertical-align:bottom;display:inline-block;]]></style>
                         </properties>
                         <tipoProperties>
                              <class><![CDATA[ita-button ita-element-animate]]></class>
                         </tipoProperties>
                    </engineElement>
                    <engineElement el_nome="divGiorniRicerca" el_tipo="74" el_colonne="0" disp_colspan="0" disp_rowspan="0" disp_acapo="0" tipo_nome="ita-div" tipo_tag="div">
                         <properties>
                              <style><![CDATA[display:inline-block;]]></style>
                         </properties>
                         <tipoProperties>
                              <class><![CDATA[ita-div]]></class>
                         </tipoProperties>
                         <engineElement el_nome="divSelectGiorni" el_tipo="7" el_colonne="0" disp_colspan="0" disp_rowspan="0" disp_acapo="0" tipo_nome="generico" tipo_tag="div">
                              <properties>
                                   <style><![CDATA[display:inline-block;]]></style>
                              </properties>
                              <engineElement el_nome="LimiteVis" el_tipo="80" el_colonne="0" disp_colspan="0" disp_rowspan="0" disp_acapo="0" tipo_nome="ita-select" tipo_tag="select">
                                   <label class="top input"><![CDATA[Limite]]></label>
                                   <properties>
                                        <class><![CDATA[ita-edit-onchange]]></class>
                                   </properties>
                                   <tipoProperties>
                                        <class><![CDATA[ita-select ita-edit]]></class>
                                   </tipoProperties>
                              </engineElement>
                         </engineElement>
                         <engineElement el_nome="divDateGiorni" el_tipo="7" el_colonne="0" disp_colspan="0" disp_rowspan="0" disp_acapo="0" tipo_nome="generico" tipo_tag="div">
                              <properties>
                                   <style><![CDATA[display:inline-block;]]></style>
                              </properties>
                              <engineElement el_nome="DaData" el_tipo="61" el_colonne="0" disp_colspan="0" disp_rowspan="0" disp_acapo="0" tipo_nome="ita-datepicker" tipo_tag="text">
                                   <label class="top input"><![CDATA[Dalla data]]></label>
                                   <properties>
                                        <size><![CDATA[12]]></size>
                                   </properties>
                                   <tipoProperties>
                                        <class><![CDATA[ita-datepicker ita-edit]]></class>
                                   </tipoProperties>
                              </engineElement>
                              <engineElement el_nome="Filtra" el_tipo="62" el_colonne="0" disp_colspan="0" disp_rowspan="0" disp_acapo="0" tipo_nome="ita-button" tipo_tag="button">
                                   <properties>
                                        <Value><![CDATA[Filtra]]></Value>
                                   </properties>
                                   <tipoProperties>
                                        <class><![CDATA[ita-button ita-element-animate]]></class>
                                   </tipoProperties>
                              </engineElement>
                         </engineElement>
                    </engineElement>
               </engineElement>
               <engineElement el_nome="divGrid" el_tipo="74" el_colonne="0" disp_colspan="0" disp_rowspan="0" disp_acapo="0" tipo_nome="ita-div" tipo_tag="div">
                    <properties>
                         <style><![CDATA[height:450px;overflow:hidden;]]></style>
                         <class><![CDATA[ita-expand-div]]></class>
                    </properties>
                    <tipoProperties>
                         <class><![CDATA[ita-div]]></class>
                    </tipoProperties>
                    <engineElement el_nome="gridProtocolli" el_tipo="91" el_colonne="20" disp_colspan="0" disp_rowspan="0" disp_acapo="0" tipo_nome="ita-jqGrid" tipo_tag="table">
                         <properties>
                              <class><![CDATA[ita-jqGrid {caption:'',width:900,height:400,rowNum:20,rowList:[], filterToolbar:true, sortname:'DATAPROT', sortorder:'desc', navGrid:true,navButtonDel:false, navButtonAdd:true, navButtonPrint:true, navButtonEdit:true,navButtonRefresh:true,autowidth:true,shrinkToFit:true,resizeToParent:true}]]></class>
                         </properties>
                         <tipoProperties>
                              <class><![CDATA[ita-jqGrid]]></class>
                         </tipoProperties>
                         <engineElement el_nome="Propar" el_tipo="57" el_colonne="0" disp_colspan="0" disp_rowspan="0" disp_acapo="0" tipo_nome="vuoto" tipo_tag="th">
                              <label class="sx ui-widget input"><![CDATA[A/P]]></label>
                         </engineElement>
                         <engineElement el_nome="Anno" el_tipo="57" el_colonne="0" disp_colspan="0" disp_rowspan="0" disp_acapo="0" tipo_nome="vuoto" tipo_tag="th">
                              <label class="sx ui-widget input"><![CDATA[Anno]]></label>
                         </engineElement>
                         <engineElement el_nome="Codice" el_tipo="57" el_colonne="0" disp_colspan="0" disp_rowspan="0" disp_acapo="0" tipo_nome="vuoto" tipo_tag="th">
                              <label class="sx ui-widget input"><![CDATA[Num.]]></label>
                         </engineElement>
                         <engineElement el_nome="Prodar" el_tipo="57" el_colonne="0" disp_colspan="0" disp_rowspan="0" disp_acapo="0" tipo_nome="vuoto" tipo_tag="th">
                              <label class="sx ui-widget input"><![CDATA[Data Reg.]]></label>
                         </engineElement>
                         <engineElement el_nome="Pronom" el_tipo="57" el_colonne="0" disp_colspan="0" disp_rowspan="0" disp_acapo="0" tipo_nome="vuoto" tipo_tag="th">
                              <label class="sx ui-widget input"><![CDATA[Provenienza/Destinatario]]></label>
                         </engineElement>
                         <engineElement el_nome="Oggde1" el_tipo="57" el_colonne="0" disp_colspan="0" disp_rowspan="0" disp_acapo="0" tipo_nome="vuoto" tipo_tag="th">
                              <label class="sx ui-widget input"><![CDATA[Oggetto]]></label>
                         </engineElement>
                         <engineElement el_nome="Notifica" el_tipo="57" el_colonne="0" disp_colspan="0" disp_rowspan="0" disp_acapo="0" tipo_nome="vuoto" tipo_tag="th">
                              <label class="sx ui-widget input"><![CDATA[Notifica]]></label>
                         </engineElement>
                         <engineElement el_nome="Lris" el_tipo="57" el_colonne="0" disp_colspan="0" disp_rowspan="0" disp_acapo="0" tipo_nome="vuoto" tipo_tag="th">
                              <label class="sx ui-widget input"><![CDATA[Ris.]]></label>
                         </engineElement>
                         <engineElement el_nome="Pronaf" el_tipo="57" el_colonne="0" disp_colspan="0" disp_rowspan="0" disp_acapo="0" tipo_nome="vuoto" tipo_tag="th">
                         </engineElement>
                         <engineElement el_nome="PROPAR" el_tipo="56" el_colonne="0" disp_colspan="0" disp_rowspan="0" disp_acapo="0" tipo_nome="generico" tipo_tag="td">
                              <properties>
                                   <width><![CDATA[30]]></width>
                                   <class><![CDATA[{search: true, stype: 'select', editoptions:{value:{'':'TUTTI', 'A':'Arrivo', 'P':'Partenza', 'C':'Doc. Formale', 'I':'Documento alla Firma'}}}]]></class>
                              </properties>
                         </engineElement>
                         <engineElement el_nome="ANNO" el_tipo="56" el_colonne="0" disp_colspan="0" disp_rowspan="0" disp_acapo="0" tipo_nome="generico" tipo_tag="td">
                              <properties>
                                   <width><![CDATA[40]]></width>
                                   <class><![CDATA[ui-state-default ui-corner-all]]></class>
                              </properties>
                         </engineElement>
                         <engineElement el_nome="CODICE" el_tipo="56" el_colonne="0" disp_colspan="0" disp_rowspan="0" disp_acapo="0" tipo_nome="generico" tipo_tag="td">
                              <properties>
                                   <width><![CDATA[50]]></width>
                                   <class><![CDATA[ui-state-default ui-corner-all]]></class>
                              </properties>
                         </engineElement>
                         <engineElement el_nome="PRODAR" el_tipo="56" el_colonne="0" disp_colspan="0" disp_rowspan="0" disp_acapo="0" tipo_nome="generico" tipo_tag="td">
                              <properties>
                                   <width><![CDATA[100]]></width>
                                   <class><![CDATA[ui-state-default ui-corner-all {formatter:eqdate}]]></class>
                              </properties>
                         </engineElement>
                         <engineElement el_nome="PRONOM" el_tipo="56" el_colonne="0" disp_colspan="0" disp_rowspan="0" disp_acapo="0" tipo_nome="generico" tipo_tag="td">
                              <properties>
                                   <width><![CDATA[200]]></width>
                                   <class><![CDATA[ui-state-default ui-corner-all]]></class>
                              </properties>
                         </engineElement>
                         <engineElement el_nome="OGGOGG" el_tipo="56" el_colonne="0" disp_colspan="0" disp_rowspan="0" disp_acapo="0" tipo_nome="generico" tipo_tag="td">
                              <properties>
                                   <width><![CDATA[250]]></width>
                                   <class><![CDATA[ui-state-default ui-corner-all]]></class>
                              </properties>
                         </engineElement>
                         <engineElement el_nome="NOTIFICA" el_tipo="56" el_colonne="0" disp_colspan="0" disp_rowspan="0" disp_acapo="0" tipo_nome="generico" tipo_tag="td">
                              <properties>
                                   <width><![CDATA[50]]></width>
                                   <class><![CDATA[ui-state-default ui-corner-all {search:false}]]></class>
                              </properties>
                         </engineElement>
                         <engineElement el_nome="PROLRIS" el_tipo="56" el_colonne="0" disp_colspan="0" disp_rowspan="0" disp_acapo="0" tipo_nome="generico" tipo_tag="td">
                              <properties>
                                   <width><![CDATA[50]]></width>
                                   <class><![CDATA[ui-state-default ui-corner-all {search:false}]]></class>
                              </properties>
                         </engineElement>
                         <engineElement el_nome="PRONAF" el_tipo="56" el_colonne="0" disp_colspan="0" disp_rowspan="0" disp_acapo="0" tipo_nome="generico" tipo_tag="td">
                              <properties>
                                   <width><![CDATA[50]]></width>
                                   <class><![CDATA[ui-state-default ui-corner-all {search:false}]]></class>
                              </properties>
                         </engineElement>
                    </engineElement>
               </engineElement>
               <engineElement el_nome="divRadio" el_tipo="7" el_colonne="0" disp_colspan="0" disp_rowspan="0" disp_acapo="0" tipo_nome="generico" tipo_tag="div">
                    <engineElement el_nome="FlagTutti" el_tipo="93" el_colonne="0" disp_colspan="0" disp_rowspan="0" disp_acapo="0" tipo_nome="ita-radio" tipo_tag="radio">
                         <label class="dx input"><![CDATA[Tutti]]></label>
                         <properties>
                              <name><![CDATA[TipoVedi]]></name>
                              <value><![CDATA[T]]></value>
                              <class><![CDATA[ita-edit-onchange]]></class>
                         </properties>
                         <tipoProperties>
                              <class><![CDATA[ita-edit ita-radio]]></class>
                         </tipoProperties>
                    </engineElement>
                    <engineElement el_nome="FlagModelli" el_tipo="93" el_colonne="0" disp_colspan="0" disp_rowspan="0" disp_acapo="0" tipo_nome="ita-radio" tipo_tag="radio">
                         <label class="dx input"><![CDATA[Solo Modelli]]></label>
                         <properties>
                              <name><![CDATA[TipoVedi]]></name>
                              <value><![CDATA[M]]></value>
                              <class><![CDATA[ita-edit-onchange]]></class>
                         </properties>
                         <tipoProperties>
                              <class><![CDATA[ita-edit ita-radio]]></class>
                         </tipoProperties>
                    </engineElement>
                    <engineElement el_nome="FlagNotifica" el_tipo="93" el_colonne="0" disp_colspan="0" disp_rowspan="0" disp_acapo="0" tipo_nome="ita-radio" tipo_tag="radio">
                         <label class="dx input"><![CDATA[Con Anomalia Notifica]]></label>
                         <properties>
                              <name><![CDATA[TipoVedi]]></name>
                              <value><![CDATA[E]]></value>
                              <class><![CDATA[ita-edit-onchange]]></class>
                         </properties>
                         <tipoProperties>
                              <class><![CDATA[ita-edit ita-radio]]></class>
                         </tipoProperties>
                    </engineElement>
                    <engineElement el_nome="FlagNonAssegnati" el_tipo="93" el_colonne="0" disp_colspan="0" disp_rowspan="0" disp_acapo="0" tipo_nome="ita-radio" tipo_tag="radio">
                         <label class="dx input"><![CDATA[Arrivi non Assegnati]]></label>
                         <properties>
                              <name><![CDATA[TipoVedi]]></name>
                              <value><![CDATA[N]]></value>
                              <class><![CDATA[ita-edit-onchange]]></class>
                         </properties>
                         <tipoProperties>
                              <class><![CDATA[ita-edit ita-radio]]></class>
                         </tipoProperties>
                    </engineElement>
                    <engineElement el_nome="FlagNonFascicolati" el_tipo="93" el_colonne="0" disp_colspan="0" disp_rowspan="0" disp_acapo="0" tipo_nome="ita-radio" tipo_tag="radio">
                         <label class="dx input"><![CDATA[Non Fascicolati]]></label>
                         <properties>
                              <name><![CDATA[TipoVedi]]></name>
                              <value><![CDATA[NF]]></value>
                              <class><![CDATA[ita-edit-onchange]]></class>
                         </properties>
                         <tipoProperties>
                              <class><![CDATA[ita-edit ita-radio]]></class>
                         </tipoProperties>
                    </engineElement>
                    <engineElement el_nome="FlagIncompleti" el_tipo="93" el_colonne="0" disp_colspan="0" disp_rowspan="0" disp_acapo="0" tipo_nome="ita-radio" tipo_tag="radio">
                         <label class="dx input"><![CDATA[Incompleti]]></label>
                         <properties>
                              <name><![CDATA[TipoVedi]]></name>
                              <value><![CDATA[IN]]></value>
                              <class><![CDATA[ita-edit-onchange]]></class>
                         </properties>
                         <tipoProperties>
                              <class><![CDATA[ita-edit ita-radio]]></class>
                         </tipoProperties>
                    </engineElement>
               </engineElement>
               <engineElement el_nome="divDocPredisposti" el_tipo="7" el_colonne="0" disp_colspan="0" disp_rowspan="0" disp_acapo="0" tipo_nome="generico" tipo_tag="div">
                    <engineElement el_nome="StatoDocPredispostoProt" el_tipo="80" el_colonne="0" disp_colspan="0" disp_rowspan="0" disp_acapo="0" tipo_nome="ita-select" tipo_tag="select">
                         <label class="sx ui-widget input"><![CDATA[Documenti Predisposti]]></label>
                         <properties>
                              <class><![CDATA[ita-edit-onchange]]></class>
                         </properties>
                         <tipoProperties>
                              <class><![CDATA[ita-select ita-edit]]></class>
                         </tipoProperties>
                    </engineElement>
               </engineElement>
               <engineElement el_nome="brF" el_tipo="72" el_colonne="0" disp_colspan="0" disp_rowspan="0" disp_acapo="0" tipo_nome="generico" tipo_tag="br">
               </engineElement>
          </engineElement>
     </engineModel>
     <info>
          <date><![CDATA[15/11/2018]]></date>
          <time><![CDATA[11:13:50]]></time>
          <user><![CDATA[a.mucci]]></user>
          <modelSHA><![CDATA[cf83fc261ff4762d6479a2d1b6767d0a5caa3456]]></modelSHA>
     </info></itaEngine>